odoo/addons/base_deterministic_session_gc/README.rst
odoo/addons/base_deterministic_session_gc/__init__.py
odoo/addons/base_deterministic_session_gc/__manifest__.py
odoo/addons/base_deterministic_session_gc/http.py
odoo/addons/base_deterministic_session_gc/data/ir_cron_data.xml
odoo/addons/base_deterministic_session_gc/i18n/base_deterministic_session_gc.pot
odoo/addons/base_deterministic_session_gc/i18n/es.po
odoo/addons/base_deterministic_session_gc/i18n/it.po
odoo/addons/base_deterministic_session_gc/models/__init__.py
odoo/addons/base_deterministic_session_gc/models/ir_autovacuum.py
odoo/addons/base_deterministic_session_gc/readme/CONFIGURE.rst
odoo/addons/base_deterministic_session_gc/readme/CONTRIBUTORS.rst
odoo/addons/base_deterministic_session_gc/readme/DESCRIPTION.rst
odoo/addons/base_deterministic_session_gc/readme/INSTALL.rst
odoo/addons/base_deterministic_session_gc/static/description/icon.png
odoo/addons/base_deterministic_session_gc/static/description/index.html
odoo14_addon_base_deterministic_session_gc-14.0.1.0.1.dist-info/METADATA
odoo14_addon_base_deterministic_session_gc-14.0.1.0.1.dist-info/WHEEL
odoo14_addon_base_deterministic_session_gc-14.0.1.0.1.dist-info/top_level.txt
odoo14_addon_base_deterministic_session_gc-14.0.1.0.1.dist-info/RECORD
