Metadata-Version: 2.1
Name: odoo14-addon-base_deterministic_session_gc
Version: 14.0.1.0.1
Summary: Provide a deterministic session garbage collection instead of the default random one
Home-page: https://github.com/OCA/server-tools
Author: Trobz,Odoo Community Association (OCA)
Author-email: support@odoo-community.org
License: AGPL-3
Classifier: Programming Language :: Python
Classifier: Framework :: Odoo
Classifier: Framework :: Odoo :: 14.0
Classifier: License :: OSI Approved :: GNU Affero General Public License v3
Requires-Python: >=3.6
Requires-Dist: odoo<14.1dev,>=14.0a
